{"v":"5.7.6","fr":29.9700012207031,"ip":0,"op":239.00000973467,"w":600,"h":600,"nm":"FAVICON","ddd":0,"assets":[],"layers":[{"ddd":0,"ind":1,"ty":4,"nm":"Layer 2","sr":1,"ks":{"o":{"a":0,"k":100,"ix":11},"r":{"a":1,"k":[{"i":{"x":[0.324],"y":[1]},"o":{"x":[0.458],"y":[0]},"t":13,"s":[0]},{"i":{"x":[0.324],"y":[1]},"o":{"x":[0.167],"y":[0]},"t":101,"s":[360]},{"i":{"x":[0.507],"y":[1]},"o":{"x":[0.713],"y":[0]},"t":118,"s":[360]},{"t":212.912508672104,"s":[0]}],"ix":10},"p":{"a":0,"k":[300,300,0],"ix":2,"l":2},"a":{"a":0,"k":[0,0,0],"ix":1,"l":2},"s":{"a":0,"k":[988.885,988.885,100],"ix":6,"l":2}},"ao":0,"shapes":[{"ty":"gr","it":[{"ind":0,"ty":"sh","ix":1,"ks":{"a":0,"k":{"i":[[2.24,4.69],[-12.25,5.85],[-3.18,0.8],[0.84,-0.4],[-2.41,-5.03],[-8.15,2.1]],"o":[[-2.4,-5.02],[3.44,-1.65],[-0.84,0.34],[-12.24,5.85],[1.73,3.62],[-11.33,4.8]],"v":[[-25.45,-3.508],[-7.63,-23.198],[2.4,-26.888],[-0.11,-25.768],[-17.92,-6.068],[-1.4,-3.878]],"c":true},"ix":2},"nm":"Path 1","mn":"ADBE Vector Shape - Group","hd":false},{"ty":"fl","c":{"a":0,"k":[0.890196084976,0.023529412225,0.070588238537,1],"ix":4},"o":{"a":0,"k":100,"ix":5},"r":1,"bm":0,"nm":"Fill 1","mn":"ADBE Vector Graphic - Fill","hd":false},{"ty":"tr","p":{"a":0,"k":[0,0],"ix":2},"a":{"a":0,"k":[0,0],"ix":1},"s":{"a":0,"k":[100,100],"ix":3},"r":{"a":0,"k":0,"ix":6},"o":{"a":0,"k":100,"ix":7},"sk":{"a":0,"k":0,"ix":4},"sa":{"a":0,"k":0,"ix":5},"nm":"Transform"}],"nm":"Group 1","np":2,"cix":2,"bm":0,"ix":1,"mn":"ADBE Vector Group","hd":false},{"ty":"gr","it":[{"ind":0,"ty":"sh","ix":1,"ks":{"a":0,"k":{"i":[[-4.69,2.24],[-5.85,-12.25],[-0.8,-3.18],[0.4,0.84],[5.03,-2.41],[-2.1,-8.15]],"o":[[5.02,-2.4],[1.65,3.44],[-0.34,-0.84],[-5.85,-12.24],[-3.62,1.73],[-4.8,-11.33]],"v":[[3.6,-25.516],[23.29,-7.696],[26.98,2.334],[25.86,-0.176],[6.16,-17.986],[3.97,-1.466]],"c":true},"ix":2},"nm":"Path 1","mn":"ADBE Vector Shape - Group","hd":false},{"ty":"fl","c":{"a":0,"k":[0.890196084976,0.023529412225,0.070588238537,1],"ix":4},"o":{"a":0,"k":100,"ix":5},"r":1,"bm":0,"nm":"Fill 1","mn":"ADBE Vector Graphic - Fill","hd":false},{"ty":"tr","p":{"a":0,"k":[0,0],"ix":2},"a":{"a":0,"k":[0,0],"ix":1},"s":{"a":0,"k":[100,100],"ix":3},"r":{"a":0,"k":0,"ix":6},"o":{"a":0,"k":100,"ix":7},"sk":{"a":0,"k":0,"ix":4},"sa":{"a":0,"k":0,"ix":5},"nm":"Transform"}],"nm":"Group 2","np":2,"cix":2,"bm":0,"ix":2,"mn":"ADBE Vector Group","hd":false},{"ty":"gr","it":[{"ind":0,"ty":"sh","ix":1,"ks":{"a":0,"k":{"i":[[-2.24,-4.69],[12.25,-5.85],[3.18,-0.8],[-0.84,0.4],[2.41,5.03],[8.15,-2.1]],"o":[[2.4,5.02],[-3.44,1.65],[0.84,-0.34],[12.24,-5.85],[-1.73,-3.62],[11.33,-4.8]],"v":[[25.519,3.508],[7.699,23.198],[-2.331,26.888],[0.179,25.768],[17.989,6.068],[1.469,3.878]],"c":true},"ix":2},"nm":"Path 1","mn":"ADBE Vector Shape - Group","hd":false},{"ty":"fl","c":{"a":0,"k":[0.890196084976,0.023529412225,0.070588238537,1],"ix":4},"o":{"a":0,"k":100,"ix":5},"r":1,"bm":0,"nm":"Fill 1","mn":"ADBE Vector Graphic - Fill","hd":false},{"ty":"tr","p":{"a":0,"k":[0,0],"ix":2},"a":{"a":0,"k":[0,0],"ix":1},"s":{"a":0,"k":[100,100],"ix":3},"r":{"a":0,"k":0,"ix":6},"o":{"a":0,"k":100,"ix":7},"sk":{"a":0,"k":0,"ix":4},"sa":{"a":0,"k":0,"ix":5},"nm":"Transform"}],"nm":"Group 3","np":2,"cix":2,"bm":0,"ix":3,"mn":"ADBE Vector Group","hd":false},{"ty":"gr","it":[{"ind":0,"ty":"sh","ix":1,"ks":{"a":0,"k":{"i":[[4.69,-2.24],[5.85,12.25],[0.8,3.18],[-0.4,-0.84],[-5.03,2.41],[2.1,8.15]],"o":[[-5.02,2.4],[-1.65,-3.44],[0.34,0.84],[5.85,12.24],[3.62,-1.73],[4.8,11.33]],"v":[[-3.6,25.571],[-23.29,7.751],[-26.98,-2.279],[-25.86,0.231],[-6.16,18.041],[-3.97,1.521]],"c":true},"ix":2},"nm":"Path 1","mn":"ADBE Vector Shape - Group","hd":false},{"ty":"fl","c":{"a":0,"k":[0.890196084976,0.023529412225,0.070588238537,1],"ix":4},"o":{"a":0,"k":100,"ix":5},"r":1,"bm":0,"nm":"Fill 1","mn":"ADBE Vector Graphic - Fill","hd":false},{"ty":"tr","p":{"a":0,"k":[0,0],"ix":2},"a":{"a":0,"k":[0,0],"ix":1},"s":{"a":0,"k":[100,100],"ix":3},"r":{"a":0,"k":0,"ix":6},"o":{"a":0,"k":100,"ix":7},"sk":{"a":0,"k":0,"ix":4},"sa":{"a":0,"k":0,"ix":5},"nm":"Transform"}],"nm":"Group 4","np":2,"cix":2,"bm":0,"ix":4,"mn":"ADBE Vector Group","hd":false}],"ip":0,"op":360.000014663101,"st":0,"bm":0}],"markers":[]}